kopi_docka/__init__.py
kopi_docka/__main__.py
kopi_docka/i18n.py
kopi_docka/types.py
kopi_docka/backends/__init__.py
kopi_docka/backends/azure.py
kopi_docka/backends/b2.py
kopi_docka/backends/base.py
kopi_docka/backends/gcs.py
kopi_docka/backends/local.py
kopi_docka/backends/rclone.py
kopi_docka/backends/s3.py
kopi_docka/backends/sftp.py
kopi_docka/backends/tailscale.py
kopi_docka/commands/__init__.py
kopi_docka/commands/backup_commands.py
kopi_docka/commands/config_commands.py
kopi_docka/commands/dependency_commands.py
kopi_docka/commands/disaster_recovery_commands.py
kopi_docka/commands/doctor_commands.py
kopi_docka/commands/dry_run_commands.py
kopi_docka/commands/repository_commands.py
kopi_docka/commands/service_commands.py
kopi_docka/commands/setup_commands.py
kopi_docka/commands/advanced/__init__.py
kopi_docka/commands/advanced/config_commands.py
kopi_docka/commands/advanced/notification_commands.py
kopi_docka/commands/advanced/repo_commands.py
kopi_docka/commands/advanced/service_commands.py
kopi_docka/commands/advanced/snapshot_commands.py
kopi_docka/commands/advanced/system_commands.py
kopi_docka/cores/__init__.py
kopi_docka/cores/backup_manager.py
kopi_docka/cores/dependency_manager.py
kopi_docka/cores/disaster_recovery_manager.py
kopi_docka/cores/docker_discovery.py
kopi_docka/cores/dry_run_manager.py
kopi_docka/cores/hooks_manager.py
kopi_docka/cores/kopia_policy_manager.py
kopi_docka/cores/notification_manager.py
kopi_docka/cores/repository_manager.py
kopi_docka/cores/restore_manager.py
kopi_docka/cores/safe_exit_manager.py
kopi_docka/cores/service_helper.py
kopi_docka/cores/service_manager.py
kopi_docka/helpers/__init__.py
kopi_docka/helpers/config.py
kopi_docka/helpers/constants.py
kopi_docka/helpers/dependency_helper.py
kopi_docka/helpers/file_operations.py
kopi_docka/helpers/logging.py
kopi_docka/helpers/process_lock.py
kopi_docka/helpers/repo_helper.py
kopi_docka/helpers/system_utils.py
kopi_docka/helpers/ui_utils.py
kopi_docka-6.0.2.dist-info/licenses/LICENSE
kopi_docka-6.0.2.dist-info/METADATA
kopi_docka-6.0.2.dist-info/WHEEL
kopi_docka-6.0.2.dist-info/entry_points.txt
kopi_docka-6.0.2.dist-info/top_level.txt
kopi_docka-6.0.2.dist-info/RECORD
