Metadata-Version: 2.4
Name: kopi-docka
Version: 6.0.2
Summary: Robust cold backups for Docker environments using Kopia
Author: Markus F. (TZERO78)
License: MIT
Project-URL: Homepage, https://github.com/TZERO78/kopi-docka
Project-URL: Documentation, https://github.com/TZERO78/kopi-docka#readme
Project-URL: Repository, https://github.com/TZERO78/kopi-docka
Project-URL: Issues, https://github.com/TZERO78/kopi-docka/issues
Keywords: docker,backup,kopia,containers,disaster-recovery
Classifier: Development Status :: 4 - Beta
Classifier: Intended Audience :: System Administrators
Classifier: Topic :: System :: Archiving :: Backup
Classifier: License :: OSI Approved :: MIT License
Classifier: Programming Language :: Python :: 3
Classifier: Programming Language :: Python :: 3.10
Classifier: Programming Language :: Python :: 3.11
Classifier: Programming Language :: Python :: 3.12
Classifier: Operating System :: POSIX :: Linux
Requires-Python: >=3.10
License-File: LICENSE
Requires-Dist: psutil>=5.9.0
Requires-Dist: typer>=0.9.0
Requires-Dist: rich>=13.0.0
Requires-Dist: rich-click>=1.7.0
Requires-Dist: apprise>=1.6.0
Requires-Dist: pydantic>=2.0.0
Provides-Extra: systemd
Requires-Dist: systemd-python>=234; extra == "systemd"
Provides-Extra: dev
Requires-Dist: pytest>=7.0.0; extra == "dev"
Requires-Dist: pytest-cov>=3.0.0; extra == "dev"
Requires-Dist: pytest-xdist>=3.0.0; extra == "dev"
Requires-Dist: pytest-randomly>=3.0.0; extra == "dev"
Requires-Dist: black>=22.0.0; extra == "dev"
Requires-Dist: flake8>=4.0.0; extra == "dev"
Requires-Dist: mypy>=1.8.0; extra == "dev"
Requires-Dist: vulture>=2.0.0; extra == "dev"
Requires-Dist: ruff>=0.1.0; extra == "dev"
Dynamic: license-file
